parser_tests/__init__.py
parser_tests/data.py
parser_tests/data/mask-match.yaml
parser_tests/data/msg-join.yaml
parser_tests/data/msg-split.yaml
parser_tests/data/userhost-split.yaml
parser_tests/data/validate-hostname.yaml
irc_parser_tests-0.0.4.dist-info/LICENSE
irc_parser_tests-0.0.4.dist-info/METADATA
irc_parser_tests-0.0.4.dist-info/WHEEL
irc_parser_tests-0.0.4.dist-info/top_level.txt
irc_parser_tests-0.0.4.dist-info/RECORD
